{"sections":{"main":{"type":"main-page","disabled":true,"settings":{"padding_top":0,"padding_bottom":0}},"contact-form":{"type":"contact-form","settings":{"contact_style":"column","image":"","image_height":"adapt","hide_image":false,"caption":"","text_style":"caption-with-letter-spacing","text_size":"medium","heading":"Contact Us","heading_size":"medium","heading_style":"default","heading_tag":"h2","text":"<p>We’d be delighted to connect with you! Our team is ready to assist. Reach out by filling in the email form below.<\/p>","button_label_1":"Contact us","button_link_1":"","button_style_secondary_1":false,"full_width":false,"hide_phone_field":false,"color_scheme":"option-2","color_scheme_1":"option-1","padding_top":12,"padding_bottom":0,"ignore_spacing":false,"image_height_mobile":"small","margin_spacing":"positive","margin_top":0}},"location-map":{"type":"location-map","settings":{"caption":"","text_style":"caption-with-letter-spacing","text_size":"medium","title":"","heading_size":"medium","heading_style":"default","heading_tag":"h2","content":"","show_contact_form":false,"hide_phone_field":true,"api_key":"","zoom_level":12,"address":"New York, USA","marker_content":"<h3><strong>New York<\/strong><\/h3><p>132 Tower str,<br\/>State Park, New York<br\/>K43 745<\/p><p><strong>(777) 777-7777<\/strong><\/p>","layout":"full-width","color_scheme":"option-1","padding_top":0,"padding_bottom":0,"ignore_spacing":false,"margin_spacing":"negative","margin_top":0}}},"order":["main","contact-form","location-map"]}